<?xml version="1.0" encoding="UTF-8"?>
<persistence version="2.2" xmlns="http://xmlns.jcp.org/xml/ns/persistence" xmlns:xsi="http://www.w3.org/2001/XMLSchema-instance" xsi:schemaLocation="http://xmlns.jcp.org/xml/ns/persistence           http://xmlns.jcp.org/xml/ns/persistence/persistence_2_2.xsd">
  <persistence-unit name="co.com.codelicht.app_SipressJavaApplication_jar_1.0PU" transaction-type="RESOURCE_LOCAL">
    <provider>org.eclipse.persistence.jpa.PersistenceProvider</provider>
    <class>domain.Perfil</class>
    <class>domain.Paciente</class>
    <class>domain.Funcion</class>
    <class>domain.Empleado</class>
    <class>domain.Servicio</class>
    <class>domain.Historial</class>
    <class>domain.Persona</class>
    <class>domain.Usuario</class>
    <class>domain.Asignacion</class>
    <properties>
      <property name="javax.persistence.jdbc.url" value="jdbc:mysql://localhost:3306/database_sipress?useSSL=false&amp;useTimezone=true&amp;serverTimezone=UTC&amp;allowPublicKeyRetrieval=true"/>
      <property name="javax.persistence.jdbc.user" value="root"/>
      <property name="javax.persistence.jdbc.driver" value="com.mysql.cj.jdbc.Driver"/>
      <property name="javax.persistence.jdbc.password" value="Tiaerpoal533"/>
    </properties>
  </persistence-unit>
</persistence>
